sphinxcontrib/sphinx_ansible/__init__.py
sphinxcontrib/sphinx_ansible/runner.py
sphinx_ansible-0.0.2.dist-info/COPYING
sphinx_ansible-0.0.2.dist-info/METADATA
sphinx_ansible-0.0.2.dist-info/WHEEL
sphinx_ansible-0.0.2.dist-info/top_level.txt
sphinx_ansible-0.0.2.dist-info/RECORD
