Metadata-Version: 2.1
Name: sphinx-ansible
Version: 0.0.2
Summary: Imagine a world where your documentation is also your Ansible playbook
Home-page: https://github.com/ansible-community/sphinx-ansible
Author: Gonéri Le Bouder
Author-email: goneri@lebouder.net
License: UNKNOWN
Platform: UNKNOWN
Requires-Dist: ansible-runner
